{
    "appKeys": {},
    "capabilities": [
        ""
    ],
    "companyName": "dmollaaliod@gmail.com",
    "enableMultiJS": false,
    "longName": "Scubawatch",
    "projectType": "native",
    "resources": {
        "media": [
            {
                "file": "images/screenshot.png",
                "menuIcon": true,
                "name": "screenshot",
                "type": "bitmap"
            }
        ]
    },
    "sdkVersion": "3",
    "shortName": "Scubawatch",
    "targetPlatforms": [
        "aplite",
        "basalt"
    ],
    "uuid": "3d701546-7fc9-4128-86c0-c61d5ec1c90a",
    "versionLabel": "2.3",
    "watchapp": {
        "watchface": false
    }
}
